{
    "providers": [
        {
            "type": "bitmap",
            "file": "minecraft:custom/icon.png",
            "ascent": -4,
            "height": 32,
            "chars": ["\uE000"]
        },
        {
            "type": "bitmap",
            "file": "minecraft:custom/icon_half.png",
            "ascent": -4,
            "height": 32,
            "chars": ["\uE001"]
        },
        {
            "type": "bitmap",
            "file": "minecraft:custom/icon_off.png",
            "ascent": -4,
            "height": 32,
            "chars": ["\uE002"]
        },
        {
            "type": "bitmap",
            "file": "minecraft:custom/smallkey.png",
            "ascent": 7,
            "height": 9,
            "chars": ["\uE003"]
        },
        {
            "type": "bitmap",
            "file": "minecraft:custom/bigkey.png",
            "ascent": 8,
            "height": 9,
            "chars": ["\uE004"]
        },
        {
            "type": "bitmap",
            "file": "minecraft:custom/load_bg.png",
            "ascent": 100,
            "height": 200,
            "chars": ["\uE006"]
        },
        {
            "type": "bitmap",
            "file": "minecraft:item/diamond.png",
            "ascent": 8,
            "height": 9,
            "chars": ["\uE005"]
        },
        {
            "type": "bitmap",
            "file": "minecraft:custom/crosshair.png",
            "ascent": 2,
            "height": 12,
            "chars": ["\uE007"]
        },
        {
            "type": "bitmap",
            "file": "minecraft:custom/icon_end.png",
            "ascent": -4,
            "height": 32,
            "chars": ["\uE008"]
        },
        {
            "type": "bitmap",
            "file": "minecraft:custom/icon_half_end.png",
            "ascent": -4,
            "height": 32,
            "chars": ["\uE009"]
        },
        {
            "type": "bitmap",
            "file": "minecraft:custom/icon_off_end.png",
            "ascent": -4,
            "height": 32,
            "chars": ["\uE010"]
        },
        {
            "type": "bitmap",
            "file": "minecraft:custom/icon_start.png",
            "ascent": -4,
            "height": 32,
            "chars": ["\uE011"]
        },
        {
            "type": "bitmap",
            "file": "minecraft:custom/icon_half_start.png",
            "ascent": -4,
            "height": 32,
            "chars": ["\uE012"]
        },
        {
            "type": "bitmap",
            "file": "minecraft:custom/icon_off_start.png",
            "ascent": -4,
            "height": 32,
            "chars": ["\uE013"]
        },
        {
            "type": "bitmap",
            "file": "minecraft:custom/black_bars.png",
            "ascent": 100,
            "height": 200,
            "chars": ["\uE014"]
        },
        {
            "type": "bitmap",
            "file": "minecraft:custom/white_bg.png",
            "ascent": 100,
            "height": 200,
            "chars": ["\uE015"]
        },
        {
            "type": "bitmap",
            "file": "minecraft:custom/blackbars.png",
            "ascent": 240,
            "height": 800,
            "chars": ["\uE016"]
        },
        {
            "type": "bitmap",
            "file": "minecraft:custom/dialoguebars.png",
            "ascent": 240,
            "height": 800,
            "chars": ["\uE017"]
        },
        {
            "type": "bitmap",
            "file": "minecraft:alttp/menu_textures/menus/inventory.png",
            "ascent": 240,
            "height": 256,
            "chars": ["\uE018"]
        },
        {
            "type": "bitmap",
            "file": "minecraft:alttp/menu_textures/menus/selector.png",
            "ascent": 240,
            "height": 240,
            "chars": ["\uE019"]
        },
        {
            "type": "bitmap",
            "file": "minecraft:alttp/menu_textures/menus/selector_diamond.png",
            "ascent": 240,
            "height": 240,
            "chars": ["\uE020"]
        },
        {
            "type": "bitmap",
            "file": "minecraft:custom/menubars.png",
            "ascent": 99,
            "height": 200,
            "chars": ["\uE021"]
        },
        {
            "type": "bitmap",
            "file": "minecraft:alttp/menu_textures/menus/transparency.png",
            "ascent": 240,
            "height": 256,
            "chars": ["\uE022"]
        },
        {
            "type": "bitmap",
            "file": "minecraft:alttp/menu_textures/menus/equipment.png",
            "ascent": 240,
            "height": 256,
            "chars": ["\uE023"]
        },
        {
            "type": "bitmap",
            "file": "minecraft:alttp/menu_textures/menus/adventure_status.png",
            "ascent": 240,
            "height": 256,
            "chars": ["\uE024"]
        },
        {
            "type": "bitmap",
            "file": "minecraft:alttp/menu_textures/menus/keys.png",
            "ascent": 240,
            "height": 256,
            "chars": ["\uE025"]
        },
        {
            "type": "bitmap",
            "file": "minecraft:item/lamp.png",
            "ascent": 16,
            "height": 16,
            "chars": ["\uE026"]
        },
        {
            "type": "bitmap",
            "file": "minecraft:item/boomerang.png",
            "ascent": 16,
            "height": 16,
            "chars": ["\uE027"]
        },
        {
            "type": "bitmap",
            "file": "minecraft:item/magical_boomerang.png",
            "ascent": 16,
            "height": 16,
            "chars": ["\uE028"]
        },
        {
            "type": "bitmap",
            "file": "minecraft:item/tnt.png",
            "ascent": 16,
            "height": 16,
            "chars": ["\uE029"]
        },
        {
            "type": "bitmap",
            "file": "minecraft:item/hookshot.png",
            "ascent": 16,
            "height": 16,
            "chars": ["\uE030"]
        }, 
        {
            "type": "bitmap",
            "file": "minecraft:item/bombos_medallion.png",
            "ascent": 16,
            "height": 16,
            "chars": ["\uE031"]
        },
        {
            "type": "bitmap",
            "file": "minecraft:item/magic_hammer.png",
            "ascent": 16,
            "height": 16,
            "chars": ["\uE032"]
        },
        {
            "type": "bitmap",
            "file": "minecraft:item/shovel.png",
            "ascent": 16,
            "height": 16,
            "chars": ["\uE033"]
        },
        {
            "type": "bitmap",
            "file": "minecraft:item/magic_powder.png",
            "ascent": 16,
            "height": 16,
            "chars": ["\uE034"]
        },
        {
            "type": "bitmap",
            "file": "minecraft:item/bug_catching_net.png",
            "ascent": 16,
            "height": 16,
            "chars": ["\uE035"]
        },
        {
            "type": "bitmap",
            "file": "minecraft:item/ether_medallion.png",
            "ascent": 16,
            "height": 16,
            "chars": ["\uE036"]
        },
        {
            "type": "bitmap",
            "file": "minecraft:item/cane_of_byrna.png",
            "ascent": 16,
            "height": 16,
            "chars": ["\uE037"]
        },
        {
            "type": "bitmap",
            "file": "minecraft:item/cane_of_somaria.png",
            "ascent": 16,
            "height": 16,
            "chars": ["\uE038"]
        },
        {
            "type": "bitmap",
            "file": "minecraft:item/magic_cape.png",
            "ascent": 16,
            "height": 16,
            "chars": ["\uE039"]
        },
        {
            "type": "bitmap",
            "file": "minecraft:item/flute.png",
            "ascent": 16,
            "height": 16,
            "chars": ["\uE040"]
        },
        {
            "type": "bitmap",
            "file": "minecraft:item/quake_medallion.png",
            "ascent": 16,
            "height": 16,
            "chars": ["\uE041"]
        },
        {
            "type": "bitmap",
            "file": "minecraft:item/fire_rod.png",
            "ascent": 16,
            "height": 16,
            "chars": ["\uE042"]
        },
        {
            "type": "bitmap",
            "file": "minecraft:item/ice_rod.png",
            "ascent": 16,
            "height": 16,
            "chars": ["\uE043"]
        },
        {
            "type": "bitmap",
            "file": "minecraft:item/locked.png",
            "ascent": 16,
            "height": 16,
            "chars": ["\uE044"]
        },
        {
            "type": "bitmap",
            "file": "minecraft:item/empty_bottle.png",
            "ascent": 16,
            "height": 16,
            "chars": ["\uE045"]
        },
        {
            "type": "bitmap",
            "file": "minecraft:alttp/menu_textures/menus/buttons/cancel.png",
            "ascent": 140,
            "height": 160,
            "chars": ["\uE046"]
        },
        {
            "type": "bitmap",
            "file": "minecraft:alttp/menu_textures/menus/buttons/left.png",
            "ascent": 140,
            "height": 160,
            "chars": ["\uE047"]
        },
        {
            "type": "bitmap",
            "file": "minecraft:alttp/menu_textures/menus/buttons/up.png",
            "ascent": 140,
            "height": 160,
            "chars": ["\uE048"]
        },
        {
            "type": "bitmap",
            "file": "minecraft:alttp/menu_textures/menus/buttons/right.png",
            "ascent": 140,
            "height": 160,
            "chars": ["\uE049"]
        },
        {
            "type": "bitmap",
            "file": "minecraft:item/empty_bomb.png",
            "ascent": 16,
            "height": 16,
            "chars": ["\uE050"]
        },
        {
            "type": "bitmap",
            "file": "minecraft:item/magic_life_potion.png",
            "ascent": 16,
            "height": 16,
            "chars": ["\uE051"]
        },
        {
            "type": "bitmap",
            "file": "minecraft:item/magic_potion.png",
            "ascent": 16,
            "height": 16,
            "chars": ["\uE052"]
        },
        {
            "type": "bitmap",
            "file": "minecraft:item/life_potion.png",
            "ascent": 16,
            "height": 16,
            "chars": ["\uE053"]
        },
        {
            "type": "bitmap",
            "file": "minecraft:item/fairy_bottle.png",
            "ascent": 16,
            "height": 16,
            "chars": ["\uE054"]
        },
        {
            "type": "bitmap",
            "file": "minecraft:item/bee_bottle.png",
            "ascent": 16,
            "height": 16,
            "chars": ["\uE055"]
        },
        {
            "type": "bitmap",
            "file": "minecraft:item/golden_bee_bottle.png",
            "ascent": 16,
            "height": 16,
            "chars": ["\uE056"]
        },
        {
            "type": "bitmap",
            "file": "space:font/space_split.png",
            "ascent": -32768,
            "height": -3,
            "chars": [
                "\uF801"
            ]
        },
        {
            "type": "bitmap",
            "file": "space:font/space_split.png",
            "ascent": -32768,
            "height": -4,
            "chars": [
                "\uF802"
            ]
        },
        {
            "type": "bitmap",
            "file": "space:font/space_split.png",
            "ascent": -32768,
            "height": -5,
            "chars": [
                "\uF803"
            ]
        },
        {
            "type": "bitmap",
            "file": "space:font/space_split.png",
            "ascent": -32768,
            "height": -6,
            "chars": [
                "\uF804"
            ]
        },
        {
            "type": "bitmap",
            "file": "space:font/space_split.png",
            "ascent": -32768,
            "height": -7,
            "chars": [
                "\uF805"
            ]
        },
        {
            "type": "bitmap",
            "file": "space:font/space_split.png",
            "ascent": -32768,
            "height": -8,
            "chars": [
                "\uF806"
            ]
        },
        {
            "type": "bitmap",
            "file": "space:font/space_split.png",
            "ascent": -32768,
            "height": -9,
            "chars": [
                "\uF807"
            ]
        },
        {
            "type": "bitmap",
            "file": "space:font/space_split.png",
            "ascent": -32768,
            "height": -10,
            "chars": [
                "\uF808"
            ]
        },
        {
            "type": "bitmap",
            "file": "space:font/space_split.png",
            "ascent": -32768,
            "height": -18,
            "chars": [
                "\uF809"
            ]
        },
        {
            "type": "bitmap",
            "file": "space:font/space_split.png",
            "ascent": -32768,
            "height": -34,
            "chars": [
                "\uF80A"
            ]
        },
        {
            "type": "bitmap",
            "file": "space:font/space_split.png",
            "ascent": -32768,
            "height": -66,
            "chars": [
                "\uF80B"
            ]
        },
        {
            "type": "bitmap",
            "file": "space:font/space_split.png",
            "ascent": -32768,
            "height": -130,
            "chars": [
                "\uF80C"
            ]
        },
        {
            "type": "bitmap",
            "file": "space:font/space_split.png",
            "ascent": -32768,
            "height": -258,
            "chars": [
                "\uF80D"
            ]
        },
        {
            "type": "bitmap",
            "file": "space:font/space_split.png",
            "ascent": -32768,
            "height": -514,
            "chars": [
                "\uF80E"
            ]
        },
        {
            "type": "bitmap",
            "file": "space:font/space_split.png",
            "ascent": -32768,
            "height": -1026,
            "chars": [
                "\uF80F"
            ]
        },
        {
            "type": "bitmap",
            "file": "space:font/space_split.png",
            "ascent": -65536,
            "height": -32770,
            "chars": [
                "\uF800"
            ]
        },
        {
            "type": "bitmap",
            "file": "space:font/space_split.png",
            "ascent": -32768,
            "height": 0,
            "chars": [
                "\uF821"
            ]
        },
        {
            "type": "bitmap",
            "file": "space:font/space_split.png",
            "ascent": -32768,
            "height": 1,
            "chars": [
                "\uF822"
            ]
        },
        {
            "type": "bitmap",
            "file": "space:font/space_split.png",
            "ascent": -32768,
            "height": 2,
            "chars": [
                "\uF823"
            ]
        },
        {
            "type": "bitmap",
            "file": "space:font/space_split.png",
            "ascent": -32768,
            "height": 3,
            "chars": [
                "\uF824"
            ]
        },
        {
            "type": "bitmap",
            "file": "space:font/space_split.png",
            "ascent": -32768,
            "height": 4,
            "chars": [
                "\uF825"
            ]
        },
        {
            "type": "bitmap",
            "file": "space:font/space_split.png",
            "ascent": -32768,
            "height": 5,
            "chars": [
                "\uF826"
            ]
        },
        {
            "type": "bitmap",
            "file": "space:font/space_split.png",
            "ascent": -32768,
            "height": 6,
            "chars": [
                "\uF827"
            ]
        },
        {
            "type": "bitmap",
            "file": "space:font/space_split.png",
            "ascent": -32768,
            "height": 7,
            "chars": [
                "\uF828"
            ]
        },
        {
            "type": "bitmap",
            "file": "space:font/space_split.png",
            "ascent": -32768,
            "height": 15,
            "chars": [
                "\uF829"
            ]
        },
        {
            "type": "bitmap",
            "file": "space:font/space_split.png",
            "ascent": -32768,
            "height": 31,
            "chars": [
                "\uF82A"
            ]
        },
        {
            "type": "bitmap",
            "file": "space:font/space_split.png",
            "ascent": -32768,
            "height": 63,
            "chars": [
                "\uF82B"
            ]
        },
        {
            "type": "bitmap",
            "file": "space:font/space_split.png",
            "ascent": -32768,
            "height": 127,
            "chars": [
                "\uF82C"
            ]
        },
        {
            "type": "bitmap",
            "file": "space:font/space_split.png",
            "ascent": -32768,
            "height": 255,
            "chars": [
                "\uF82D"
            ]
        },
        {
            "type": "bitmap",
            "file": "space:font/space_split.png",
            "ascent": -32768,
            "height": 511,
            "chars": [
                "\uF82E"
            ]
        },
        {
            "type": "bitmap",
            "file": "space:font/space_split.png",
            "ascent": -32768,
            "height": 1023,
            "chars": [
                "\uF82F"
            ]
        },
        {
            "type": "bitmap",
            "file": "space:font/space_split.png",
            "ascent": -65536,
            "height": 32767,
            "chars": [
                "\uF820"
            ]
        },
        {
            "type": "bitmap",
            "file": "space:font/space_nosplit.png",
            "ascent": -32768,
            "height": -3,
            "chars": [
                "\uF811"
            ]
        },
        {
            "type": "bitmap",
            "file": "space:font/space_nosplit.png",
            "ascent": -32768,
            "height": -4,
            "chars": [
                "\uF812"
            ]
        },
        {
            "type": "bitmap",
            "file": "space:font/space_nosplit.png",
            "ascent": -32768,
            "height": -5,
            "chars": [
                "\uF813"
            ]
        },
        {
            "type": "bitmap",
            "file": "space:font/space_nosplit.png",
            "ascent": -32768,
            "height": -6,
            "chars": [
                "\uF814"
            ]
        },
        {
            "type": "bitmap",
            "file": "space:font/space_nosplit.png",
            "ascent": -32768,
            "height": -7,
            "chars": [
                "\uF815"
            ]
        },
        {
            "type": "bitmap",
            "file": "space:font/space_nosplit.png",
            "ascent": -32768,
            "height": -8,
            "chars": [
                "\uF816"
            ]
        },
        {
            "type": "bitmap",
            "file": "space:font/space_nosplit.png",
            "ascent": -32768,
            "height": -9,
            "chars": [
                "\uF817"
            ]
        },
        {
            "type": "bitmap",
            "file": "space:font/space_nosplit.png",
            "ascent": -32768,
            "height": -10,
            "chars": [
                "\uF818"
            ]
        },
        {
            "type": "bitmap",
            "file": "space:font/space_nosplit.png",
            "ascent": -32768,
            "height": -18,
            "chars": [
                "\uF819"
            ]
        },
        {
            "type": "bitmap",
            "file": "space:font/space_nosplit.png",
            "ascent": -32768,
            "height": -34,
            "chars": [
                "\uF81A"
            ]
        },
        {
            "type": "bitmap",
            "file": "space:font/space_nosplit.png",
            "ascent": -32768,
            "height": -66,
            "chars": [
                "\uF81B"
            ]
        },
        {
            "type": "bitmap",
            "file": "space:font/space_nosplit.png",
            "ascent": -32768,
            "height": -130,
            "chars": [
                "\uF81C"
            ]
        },
        {
            "type": "bitmap",
            "file": "space:font/space_nosplit.png",
            "ascent": -32768,
            "height": -258,
            "chars": [
                "\uF81D"
            ]
        },
        {
            "type": "bitmap",
            "file": "space:font/space_nosplit.png",
            "ascent": -32768,
            "height": -514,
            "chars": [
                "\uF81E"
            ]
        },
        {
            "type": "bitmap",
            "file": "space:font/space_nosplit.png",
            "ascent": -32768,
            "height": -1026,
            "chars": [
                "\uF81F"
            ]
        },
        {
            "type": "bitmap",
            "file": "space:font/space_nosplit.png",
            "ascent": -65536,
            "height": -32770,
            "chars": [
                "\uF810"
            ]
        },
        {
            "type": "bitmap",
            "file": "space:font/space_nosplit.png",
            "ascent": -32768,
            "height": 0,
            "chars": [
                "\uF831"
            ]
        },
        {
            "type": "bitmap",
            "file": "space:font/space_nosplit.png",
            "ascent": -32768,
            "height": 1,
            "chars": [
                "\uF832"
            ]
        },
        {
            "type": "bitmap",
            "file": "space:font/space_nosplit.png",
            "ascent": -32768,
            "height": 2,
            "chars": [
                "\uF833"
            ]
        },
        {
            "type": "bitmap",
            "file": "space:font/space_nosplit.png",
            "ascent": -32768,
            "height": 3,
            "chars": [
                "\uF834"
            ]
        },
        {
            "type": "bitmap",
            "file": "space:font/space_nosplit.png",
            "ascent": -32768,
            "height": 4,
            "chars": [
                "\uF835"
            ]
        },
        {
            "type": "bitmap",
            "file": "space:font/space_nosplit.png",
            "ascent": -32768,
            "height": 5,
            "chars": [
                "\uF836"
            ]
        },
        {
            "type": "bitmap",
            "file": "space:font/space_nosplit.png",
            "ascent": -32768,
            "height": 6,
            "chars": [
                "\uF837"
            ]
        },
        {
            "type": "bitmap",
            "file": "space:font/space_nosplit.png",
            "ascent": -32768,
            "height": 7,
            "chars": [
                "\uF838"
            ]
        },
        {
            "type": "bitmap",
            "file": "space:font/space_nosplit.png",
            "ascent": -32768,
            "height": 15,
            "chars": [
                "\uF839"
            ]
        },
        {
            "type": "bitmap",
            "file": "space:font/space_nosplit.png",
            "ascent": -32768,
            "height": 31,
            "chars": [
                "\uF83A"
            ]
        },
        {
            "type": "bitmap",
            "file": "space:font/space_nosplit.png",
            "ascent": -32768,
            "height": 63,
            "chars": [
                "\uF83B"
            ]
        },
        {
            "type": "bitmap",
            "file": "space:font/space_nosplit.png",
            "ascent": -32768,
            "height": 127,
            "chars": [
                "\uF83C"
            ]
        },
        {
            "type": "bitmap",
            "file": "space:font/space_nosplit.png",
            "ascent": -32768,
            "height": 255,
            "chars": [
                "\uF83D"
            ]
        },
        {
            "type": "bitmap",
            "file": "space:font/space_nosplit.png",
            "ascent": -32768,
            "height": 511,
            "chars": [
                "\uF83E"
            ]
        },
        {
            "type": "bitmap",
            "file": "space:font/space_nosplit.png",
            "ascent": -32768,
            "height": 1023,
            "chars": [
                "\uF83F"
            ]
        },
        {
            "type": "bitmap",
            "file": "space:font/space_nosplit.png",
            "ascent": -65536,
            "height": 32767,
            "chars": [
                "\uF830"
            ]
        }
    ]
}